[{"name": "acoustic.IsotropicAcoustic.time_forward", "idx": 0, "pretty_name": "acoustic.IsotropicAcoustic.time_forward((492, 492, 492), 12)", "last_rev": 11197, "last_value": 9.389790843999975, "last_err": 0.17001452610729745, "prev_value": null, "change_rev": null}, {"name": "codegen.TTI.time_adjoint", "idx": null, "pretty_name": "codegen.TTI.time_adjoint", "last_rev": 11197, "last_value": 23.32905061349996, "last_err": 0.23811035976031664, "prev_value": null, "change_rev": null}, {"name": "codegen.TTI.time_forward", "idx": null, "pretty_name": "codegen.TTI.time_forward", "last_rev": 11197, "last_value": 9.594104614000003, "last_err": 0.15413712020277914, "prev_value": null, "change_rev": null}, {"name": "simple_operators.time_basic", "idx": null, "pretty_name": "simple_operators.time_basic", "last_rev": 11197, "last_value": 1.4538348204999636, "last_err": 0.026400204242486253, "prev_value": 1.670317567000012, "change_rev": [11002, 11014]}, {"name": "simple_operators.time_gaussian_smoother", "idx": null, "pretty_name": "simple_operators.time_gaussian_smoother", "last_rev": 11197, "last_value": 1.055762690999984, "last_err": 0.020909465386373637, "prev_value": null, "change_rev": null}, {"name": "simple_operators.time_laplacian", "idx": null, "pretty_name": "simple_operators.time_laplacian", "last_rev": 11197, "last_value": 1.7390461159999973, "last_err": 0.036535933313090546, "prev_value": null, "change_rev": null}, {"name": "simple_operators.time_norm", "idx": null, "pretty_name": "simple_operators.time_norm", "last_rev": 11197, "last_value": 0.42864172899999176, "last_err": 0.004109155287326613, "prev_value": null, "change_rev": null}]