[{"name": "acoustic.IsotropicAcoustic.time_forward", "idx": 0, "pretty_name": "acoustic.IsotropicAcoustic.time_forward((492, 492, 492), 12)", "last_rev": 13089, "last_value": 9.410433697999991, "last_err": 0.38439773521135234, "prev_value": null, "change_rev": null}, {"name": "codegen.TTI.time_adjoint", "idx": null, "pretty_name": "codegen.TTI.time_adjoint", "last_rev": 13089, "last_value": 14.567349837499961, "last_err": 0.7342620792840984, "prev_value": 44.17137002550001, "change_rev": [12715, 12726]}, {"name": "codegen.TTI.time_forward", "idx": null, "pretty_name": "codegen.TTI.time_forward", "last_rev": 13089, "last_value": 9.710218542000064, "last_err": 0.4597096479525009, "prev_value": 29.538365609500033, "change_rev": [12715, 12726]}, {"name": "simple_operators.time_basic", "idx": null, "pretty_name": "simple_operators.time_basic", "last_rev": 13089, "last_value": 1.5163838665000071, "last_err": 0.11651591203817833, "prev_value": null, "change_rev": null}, {"name": "simple_operators.time_gaussian_smoother", "idx": null, "pretty_name": "simple_operators.time_gaussian_smoother", "last_rev": 13089, "last_value": 1.046285438500007, "last_err": 0.02821339215874815, "prev_value": 3.180448356999989, "change_rev": [12715, 12726]}, {"name": "simple_operators.time_laplacian", "idx": null, "pretty_name": "simple_operators.time_laplacian", "last_rev": 13089, "last_value": 1.8845442179999736, "last_err": 0.0630684854834584, "prev_value": 1.7240304369999535, "change_rev": [11509, 11513]}, {"name": "simple_operators.time_norm", "idx": null, "pretty_name": "simple_operators.time_norm", "last_rev": 13089, "last_value": 0.4322904944999948, "last_err": 0.018504570628540603, "prev_value": null, "change_rev": null}]