[{"name": "acoustic.IsotropicAcoustic.time_forward", "idx": 0, "pretty_name": "acoustic.IsotropicAcoustic.time_forward((492, 492, 492), 12)", "last_rev": 11080, "last_value": 9.402510873500006, "last_err": 0.10153704846510216, "prev_value": null, "change_rev": null}, {"name": "codegen.TTI.time_adjoint", "idx": null, "pretty_name": "codegen.TTI.time_adjoint", "last_rev": 11080, "last_value": 23.47728256450003, "last_err": 0.16709983594572483, "prev_value": null, "change_rev": null}, {"name": "codegen.TTI.time_forward", "idx": null, "pretty_name": "codegen.TTI.time_forward", "last_rev": 11080, "last_value": 9.35350958899997, "last_err": 0.0, "prev_value": 9.720083953499966, "change_rev": [11070, 11080]}, {"name": "simple_operators.time_basic", "idx": null, "pretty_name": "simple_operators.time_basic", "last_rev": 11080, "last_value": 1.670317567000012, "last_err": 0.0, "prev_value": 1.5135720530000185, "change_rev": [11070, 11080]}, {"name": "simple_operators.time_gaussian_smoother", "idx": null, "pretty_name": "simple_operators.time_gaussian_smoother", "last_rev": 11080, "last_value": 1.0646834534999812, "last_err": 0.009799079456696206, "prev_value": null, "change_rev": null}, {"name": "simple_operators.time_laplacian", "idx": null, "pretty_name": "simple_operators.time_laplacian", "last_rev": 11080, "last_value": 1.746328193499977, "last_err": 0.031659700570873035, "prev_value": null, "change_rev": null}, {"name": "simple_operators.time_norm", "idx": null, "pretty_name": "simple_operators.time_norm", "last_rev": 11080, "last_value": 0.42864172899999176, "last_err": 0.003652129149047676, "prev_value": null, "change_rev": null}]