[{"name": "acoustic.IsotropicAcoustic.time_forward", "idx": 0, "pretty_name": "acoustic.IsotropicAcoustic.time_forward((492, 492, 492), 12)", "last_rev": 13432, "last_value": 9.043120771995746, "last_err": 0.49447131310030407, "prev_value": null, "change_rev": null}, {"name": "codegen.TTI.time_adjoint", "idx": null, "pretty_name": "codegen.TTI.time_adjoint", "last_rev": 13432, "last_value": 9.47871546796523, "last_err": 0.11102058606935136, "prev_value": 9.890582072985126, "change_rev": [13103, 13140]}, {"name": "codegen.TTI.time_forward", "idx": null, "pretty_name": "codegen.TTI.time_forward", "last_rev": 13432, "last_value": 6.573197357996833, "last_err": 0.22487233343861773, "prev_value": 7.1461984049965395, "change_rev": [12973, 12978]}, {"name": "simple_operators.time_basic", "idx": null, "pretty_name": "simple_operators.time_basic", "last_rev": 13432, "last_value": 2.4706354344962165, "last_err": 0.34397987759585463, "prev_value": null, "change_rev": null}, {"name": "simple_operators.time_gaussian_smoother", "idx": null, "pretty_name": "simple_operators.time_gaussian_smoother", "last_rev": 13432, "last_value": 0.899961840999822, "last_err": 0.030403979932625433, "prev_value": null, "change_rev": null}, {"name": "simple_operators.time_laplacian", "idx": null, "pretty_name": "simple_operators.time_laplacian", "last_rev": 13432, "last_value": 2.665074367017951, "last_err": 0.1977904065538499, "prev_value": null, "change_rev": null}, {"name": "simple_operators.time_norm", "idx": null, "pretty_name": "simple_operators.time_norm", "last_rev": 13432, "last_value": 0.3748295553959906, "last_err": 0.020069496275647563, "prev_value": null, "change_rev": null}]