[{"name": "acoustic.IsotropicAcoustic.time_forward", "idx": 0, "pretty_name": "acoustic.IsotropicAcoustic.time_forward((492, 492, 492), 12)", "last_rev": 13180, "last_value": 9.172825903486228, "last_err": 1.1090475249019212, "prev_value": null, "change_rev": null}, {"name": "codegen.TTI.time_adjoint", "idx": null, "pretty_name": "codegen.TTI.time_adjoint", "last_rev": 13180, "last_value": 10.33317417249782, "last_err": 0.13765281002373486, "prev_value": 9.309056001948193, "change_rev": [13051, 13093]}, {"name": "codegen.TTI.time_forward", "idx": null, "pretty_name": "codegen.TTI.time_forward", "last_rev": 13180, "last_value": 6.639583139505703, "last_err": 0.0, "prev_value": 7.428106535488041, "change_rev": [13167, 13180]}, {"name": "simple_operators.time_basic", "idx": null, "pretty_name": "simple_operators.time_basic", "last_rev": 13180, "last_value": 2.522164342517499, "last_err": 0.44557811057659813, "prev_value": null, "change_rev": null}, {"name": "simple_operators.time_gaussian_smoother", "idx": null, "pretty_name": "simple_operators.time_gaussian_smoother", "last_rev": 13180, "last_value": 0.8794406209999579, "last_err": 0.02109456975591188, "prev_value": null, "change_rev": null}, {"name": "simple_operators.time_laplacian", "idx": null, "pretty_name": "simple_operators.time_laplacian", "last_rev": 13180, "last_value": 2.665074367017951, "last_err": 0.0, "prev_value": 3.5567765519954264, "change_rev": [13167, 13180]}, {"name": "simple_operators.time_norm", "idx": null, "pretty_name": "simple_operators.time_norm", "last_rev": 13180, "last_value": 0.3652454148977995, "last_err": 0.03300434399095503, "prev_value": null, "change_rev": null}]