[{"name": "acoustic.IsotropicAcoustic.time_forward", "idx": 0, "pretty_name": "acoustic.IsotropicAcoustic.time_forward((492, 492, 492), 12)", "last_rev": 14129, "last_value": 8.83668280247366, "last_err": 0.21863790508710804, "prev_value": 8.558000238495879, "change_rev": [13821, 13832]}, {"name": "arguments.Processing.time_processing", "idx": null, "pretty_name": "arguments.Processing.time_processing", "last_rev": 14129, "last_value": 0.007599187490995973, "last_err": 0.00010801468255874362, "prev_value": null, "change_rev": null}, {"name": "codegen.TTI.time_adjoint", "idx": null, "pretty_name": "codegen.TTI.time_adjoint", "last_rev": 14129, "last_value": 8.880210377508774, "last_err": 0.19541780099007697, "prev_value": 8.080129902926274, "change_rev": [13821, 13832]}, {"name": "codegen.TTI.time_forward", "idx": null, "pretty_name": "codegen.TTI.time_forward", "last_rev": 14129, "last_value": 6.610874299018178, "last_err": 0.13631979367209424, "prev_value": 7.095728317013709, "change_rev": [13400, 13413]}, {"name": "simple_operators.time_basic", "idx": null, "pretty_name": "simple_operators.time_basic", "last_rev": 14129, "last_value": 2.3423044185001345, "last_err": 0.056289504616558225, "prev_value": 2.512958139879629, "change_rev": [13154, 13176]}, {"name": "simple_operators.time_gaussian_smoother", "idx": null, "pretty_name": "simple_operators.time_gaussian_smoother", "last_rev": 14129, "last_value": 0.8912148614763282, "last_err": 0.018686766443320377, "prev_value": null, "change_rev": null}, {"name": "simple_operators.time_laplacian", "idx": null, "pretty_name": "simple_operators.time_laplacian", "last_rev": 14129, "last_value": 2.5538914409989957, "last_err": 0.04041475023700665, "prev_value": 2.517146586003946, "change_rev": [13329, 13332]}, {"name": "simple_operators.time_norm", "idx": null, "pretty_name": "simple_operators.time_norm", "last_rev": 14129, "last_value": 0.3617344240046805, "last_err": 0.013506168822014655, "prev_value": null, "change_rev": null}]